{
  "dataset": "oracle_kri16_demod",
  "method": "HyperRSI",
  "task": "open_set_rejection",
  "seed": 42,
  "threshold_strategy_used": "center_cosine_val_known_quantile",
  "threshold_mode": "center_cosine_val_known_quantile",
  "threshold": 0.9995539605617523,
  "threshold_quantile": 0.05,
  "number_of_tx": 16,
  "number_of_rx_used": "N/A",
  "rx_mode": "not_applicable",
  "rx_used": [
    "N/A"
  ],
  "known_tx_list": [
    "1",
    "2",
    "3",
    "4",
    "5",
    "7",
    "9",
    "13",
    "14",
    "15"
  ],
  "unknown_tx_list": [
    "17",
    "18",
    "19",
    "25",
    "26",
    "32"
  ],
  "known_classes": 10,
  "unknown_classes": 6,
  "train_sample_count": 28000,
  "val_sample_count": 4000,
  "test_known_sample_count": 8000,
  "test_unknown_sample_count": 24000,
  "split_file": "D:\\learn_pytorch\\笔记\\方案\\os_sei_code\\data\\splits\\oracle\\oracle_main_sorted_k10_u6.json",
  "output_dir": "D:\\learn_pytorch\\笔记\\方案\\os_sei_code\\Comparison method\\adapted_results\\smoke\\oracle_kri16_demod\\hyperrsi",
  "best_val_acc": 0.1,
  "best_epoch": 0,
  "training_status": "reused_checkpoint",
  "overall_accuracy": 0.10606060606060606,
  "macro_precision": 0.11855784367148003,
  "macro_recall": 0.10606060606060605,
  "macro_f1": 0.10669534336671548,
  "weighted_f1": 0.10669534336671548,
  "known_accuracy": 0.09166666666666666,
  "unknown_precision": 0.3333333333333333,
  "unknown_recall": 0.25,
  "known_fpr_as_unknown": 0.05,
  "unknown_false_accept_rate": 0.75,
  "auroc": 0.6434027777777777,
  "fpr95": 0.9416666666666667,
  "oscr": 0.05954861111111111
}